uwu_codec/__init__.py
uwu_codec/codec.py
uwu_codec/stream_reader.py
uwu_codec/stream_writer.py
uwu_codec-1.2.dist-info/METADATA
uwu_codec-1.2.dist-info/WHEEL
uwu_codec-1.2.dist-info/top_level.txt
uwu_codec-1.2.dist-info/RECORD
