Metadata-Version: 2.1
Name: uwu-codec
Version: 1.2
Summary: Yep, your eyes are not deceiving you. An UwU codec. 😳 Currently WIP...
Author-email: Goldy <goldy@devgoldy.xyz>
Project-URL: GitHub, https://github.com/THEGOLDENPRO/uwu-codec
Project-URL: BugTracker, https://github.com/THEGOLDENPRO/uwu-codec/issues
Keywords: uwu,UwU,UwU Codec,uwu-codec,uwu encoder,uwu decoder
Classifier: Operating System :: Microsoft :: Windows :: Windows 11
Classifier: Operating System :: Microsoft :: Windows :: Windows 10
Classifier: Operating System :: POSIX :: Linux
Classifier: License :: OSI Approved :: GNU General Public License v3 (GPLv3)
Classifier: Programming Language :: Python :: 3.8
Classifier: Programming Language :: Python :: 3.9
Classifier: Programming Language :: Python :: 3.10
Classifier: Programming Language :: Python :: 3.11
Requires-Python: >=3.8
Requires-Dist: requests
Requires-Dist: devgoldyutils (>=2.5.1)
Requires-Dist: importlib-metadata ; python_version < "3.8"
Provides-Extra: dev
Requires-Dist: pytest ; extra == 'dev'
Requires-Dist: pytest-cov ; extra == 'dev'
Requires-Dist: ruff ; extra == 'dev'
